Tangiball.py
__init__.py
tangiball-0.4.2.dist-info/METADATA
tangiball-0.4.2.dist-info/WHEEL
tangiball-0.4.2.dist-info/entry_points.txt
tangiball-0.4.2.dist-info/RECORD
