Metadata-Version: 2.1
Name: tangiball
Version: 0.4.2
Summary: Small package to identify and analyse peaks in a specific time-series
Project-URL: Homepage, https://github.com/D-I-S-C-U-S/Tangiball
Author-email: Joseph Starkey <jds40@sussex.ac.uk>
Classifier: License :: OSI Approved :: MIT License
Classifier: Operating System :: OS Independent
Classifier: Programming Language :: Python :: 3
Requires-Python: >=3.9
